{
  "collapse-filter": false,
  "search": "",
  "showTags": false,
  "showAttachments": false,
  "hideUnresolved": true,
  "showOrphans": true,
  "collapse-color-groups": false,
  "colorGroups": [
    {
      "query": "tag:#react ",
      "color": {
        "a": 1,
        "rgb": 7536895
      }
    },
    {
      "query": "tag:#react-hooks",
      "color": {
        "a": 1,
        "rgb": 582156
      }
    },
    {
      "query": "tag:#react-libraries",
      "color": {
        "a": 1,
        "rgb": 16014685
      }
    },
    {
      "query": "tag:#js-ts",
      "color": {
        "a": 1,
        "rgb": 15925135
      }
    },
    {
      "query": "tag:#methods",
      "color": {
        "a": 1,
        "rgb": 16756224
      }
    },
    {
      "query": "tag:#info",
      "color": {
        "a": 1,
        "rgb": 40171
      }
    },
    {
      "query": "tag:#фишки",
      "color": {
        "a": 1,
        "rgb": 11010048
      }
    },
    {
      "query": "tag:#redux",
      "color": {
        "a": 1,
        "rgb": 5645934
      }
    },
    {
      "query": "tag:#tests",
      "color": {
        "a": 1,
        "rgb": 1114367
      }
    },
    {
      "query": "tag:#ClassComponents",
      "color": {
        "a": 1,
        "rgb": 5072414
      }
    }
  ],
  "collapse-display": false,
  "showArrow": true,
  "textFadeMultiplier": -2.7,
  "nodeSizeMultiplier": 1.60208333333333,
  "lineSizeMultiplier": 1.42708333333333,
  "collapse-forces": false,
  "centerStrength": 0.744047619047619,
  "repelStrength": 20,
  "linkStrength": 1,
  "linkDistance": 210,
  "scale": 0.50876188557928,
  "close": true
}